hyfi/__cli__.py
hyfi/__click__.py
hyfi/__init__.py
hyfi/_version.py
hyfi/about/__init__.py
hyfi/about/about.py
hyfi/batch/__init__.py
hyfi/batch/batch.py
hyfi/composer/__init__.py
hyfi/composer/composer.py
hyfi/composer/config.py
hyfi/composer/docs.py
hyfi/composer/generator.py
hyfi/composer/help.py
hyfi/composer/model.py
hyfi/composer/settings.py
hyfi/composer/utils.py
hyfi/conf/__init__.py
hyfi/conf/about/__init__.yaml
hyfi/conf/batch/__init__.yaml
hyfi/conf/cmd/__init__.yaml
hyfi/conf/cmd/about.yaml
hyfi/conf/cmd/copy_conf.yaml
hyfi/conf/cmd/run_task.yaml
hyfi/conf/cmd/run_workflow.yaml
hyfi/conf/composer/__init__.yaml
hyfi/conf/config.yaml
hyfi/conf/copier/__init__.yaml
hyfi/conf/docs/__init__.yaml
hyfi/conf/env/__init__.yaml
hyfi/conf/env/__project__.yaml
hyfi/conf/hydra/help/help.yaml
hyfi/conf/hydra/job_logging/custom.yaml
hyfi/conf/joblib/__init__.yaml
hyfi/conf/mode/__debug__.yaml
hyfi/conf/mode/__hydra_debug__.yaml
hyfi/conf/mode/__info__.yaml
hyfi/conf/mode/__init__.yaml
hyfi/conf/module/__init__.yaml
hyfi/conf/path/__batch__.yaml
hyfi/conf/path/__init__.yaml
hyfi/conf/path/__project__.yaml
hyfi/conf/path/__task__.yaml
hyfi/conf/path/dirnames/__init__.yaml
hyfi/conf/pipe/__dataframe__.yaml
hyfi/conf/pipe/__dataframe_external_funcs__.yaml
hyfi/conf/pipe/__dataframe_instance_methods__.yaml
hyfi/conf/pipe/__general_external_funcs__.yaml
hyfi/conf/pipe/__general_instance_methods__.yaml
hyfi/conf/pipe/__init__.yaml
hyfi/conf/pipe/dataframe_combine_str_columns.yaml
hyfi/conf/pipe/dataframe_drop.yaml
hyfi/conf/pipe/dataframe_drop_columns.yaml
hyfi/conf/pipe/dataframe_eval_columns.yaml
hyfi/conf/pipe/dataframe_eval_columns_with_pd_eval.yaml
hyfi/conf/pipe/dataframe_print_head_and_tail.yaml
hyfi/conf/pipe/dataframe_select_columns.yaml
hyfi/conf/pipe/dataframe_split_str_column.yaml
hyfi/conf/pipe/dataset_remove_columns.yaml
hyfi/conf/pipe/dataset_to_pandas.yaml
hyfi/conf/pipe/dict_to_dataframe.yaml
hyfi/conf/pipe/filter_and_sample_data.yaml
hyfi-1.37.0.dist-info/LICENSE
hyfi-1.37.0.dist-info/METADATA
hyfi-1.37.0.dist-info/WHEEL
hyfi-1.37.0.dist-info/entry_points.txt
hyfi-1.37.0.dist-info/RECORD
