Metadata-Version: 2.1
Name: hyfi
Version: 1.37.0
Summary: Hydra Fast Interface (Hydra and Pydantic based interface framework)
Home-page: https://hyfi.entelecheia.ai
License: MIT
Author: Young Joon Lee
Author-email: entelecheia@hotmail.com
Requires-Python: >=3.9,<3.13
Classifier: License :: OSI Approved :: MIT License
Classifier: Programming Language :: Python :: 3
Classifier: Programming Language :: Python :: 3.9
Classifier: Programming Language :: Python :: 3.10
Classifier: Programming Language :: Python :: 3.11
Classifier: Programming Language :: Python :: 3.12
Provides-Extra: all
Provides-Extra: cache
Provides-Extra: ipython
Requires-Dist: cached-path (>=1.6.2,<2.0.0) ; extra == "cache" or extra == "all"
Requires-Dist: chardet (<=5.2.0)
Requires-Dist: click (<=8.1.7)
Requires-Dist: colorama (>=0.4.3,<0.5.0)
Requires-Dist: datasets (>=2.0.0,<=2.21.0)
Requires-Dist: gdown (<=5.2.0)
Requires-Dist: hydra-colorlog (>=1.2.0,<2.0.0)
Requires-Dist: hydra-core (>=1.3.2,<2.0.0)
Requires-Dist: ipython (<=8.18.1) ; extra == "ipython" or extra == "all"
Requires-Dist: ipython-autotime (>=0.3.1,<0.4.0) ; extra == "ipython" or extra == "all"
Requires-Dist: ipywidgets (>=8.0.6,<9.0.0) ; extra == "ipython" or extra == "all"
Requires-Dist: joblib (>=1.2.0,<=1.4.2)
Requires-Dist: loky (>=3.4.1,<4.0.0) ; extra == "all"
Requires-Dist: matplotlib (<=3.9.2)
Requires-Dist: numba (>=0.58,<0.61) ; extra == "all"
Requires-Dist: numpy (>=1.26.0,<=2.0.2)
Requires-Dist: p-tqdm (>=1.4.0,<2.0.0) ; extra == "all"
Requires-Dist: pandas (>=1.5.3,<=2.2.2)
Requires-Dist: pathspec (>=0.9.0)
Requires-Dist: pyarrow (<=17.0.0)
Requires-Dist: pydantic (>=2.3.0,<3.0.0)
Requires-Dist: pydantic-settings (>=2.0.1,<3.0.0)
Requires-Dist: python-dotenv (>=1.0.0,<2.0.0)
Requires-Dist: ray (>=2.5.1,<3.0.0) ; extra == "all"
Requires-Dist: scipy (>1.10.0,<=1.13.1)
Requires-Dist: tqdm (>=4.64.1,<5.0.0)
Project-URL: Repository, https://github.com/entelecheia/hyfi
